olang_semantic_doc_search-1.0.0.dist-info/licenses/LICENSE
semantic_doc_search/__init__.py
semantic_doc_search/core.py
semantic_doc_search/server.py
olang_semantic_doc_search-1.0.0.dist-info/METADATA
olang_semantic_doc_search-1.0.0.dist-info/WHEEL
olang_semantic_doc_search-1.0.0.dist-info/entry_points.txt
olang_semantic_doc_search-1.0.0.dist-info/top_level.txt
olang_semantic_doc_search-1.0.0.dist-info/RECORD
